chemui/__init__.py
chemui/example.py
chemui/frontend/build/RDKit_minimal.js
chemui/frontend/build/RDKit_minimal.wasm
chemui/frontend/build/bootstrap.min.css
chemui/frontend/build/index.html
chemui/frontend/build/assets/cells-D9Q81GMa.jpg
chemui/frontend/build/assets/emotion-react-jsx-runtime.browser.esm-BsMRgtqW.js
chemui/frontend/build/assets/emotion-react-jsx-runtime.browser.esm-Bz_1IhDI.js
chemui/frontend/build/assets/index-BF7rYsVg.js
chemui/frontend/build/assets/index-DhPTaHLS.js
chemui/frontend/build/assets/index-rj7FyCJc.css
chemui/frontend/build/assets/index.modern-Dnyn1k-Y.js
chemui/frontend/build/assets/index.modern-DojmF5J0.js
chemui/frontend/build/assets/index.modern-dffdbebd-BY3gR7Lc.js
chemui/frontend/build/assets/index.modern-dffdbebd-DHq58uA1.js
chemui/frontend/build/assets/nebula_back6-DGSZ_tzT.jpg
chemui/frontend/build/assets/nebula_bottom4-DgUpJxjp.jpg
chemui/frontend/build/assets/nebula_front5-CWqbzonZ.jpg
chemui/frontend/build/assets/nebula_left2-Da3VdN9a.jpg
chemui/frontend/build/assets/nebula_right1-BWVtsnot.jpg
chemui/frontend/build/assets/nebula_top3-CfldhfdM.jpg
streamlit_chemui-0.0.1.dist-info/LICENSE
streamlit_chemui-0.0.1.dist-info/METADATA
streamlit_chemui-0.0.1.dist-info/WHEEL
streamlit_chemui-0.0.1.dist-info/top_level.txt
streamlit_chemui-0.0.1.dist-info/RECORD
